sablier.py
setup.py
sablier.egg-info/PKG-INFO
sablier.egg-info/SOURCES.txt
sablier.egg-info/dependency_links.txt
sablier.egg-info/requires.txt
sablier.egg-info/top_level.txt