Metadata-Version: 1.0
Name: sablier
Version: 0.2.2
Summary: Python API to play with date, time and timezones
Home-page: https://github.com/3kwa/sablier
Author: Eugene Van den Bulke
Author-email: eugene.vandenbulke@gmail.com
License: unlicense
Platform: UNKNOWN
